telewrap/__init__.py
telewrap/cli/__init__.py
telewrap/cli/_config.py
telewrap/cli/cli.py
telewrap/core/__init__.py
telewrap/core/bot.py
telewrap/core/constants.py
telewrap/core/message_funcs.py
telewrap/core/raising_thread.py
telewrap/core/shell_command.py
telewrap/core/singleton.py
telewrap-0.2.1.dist-info/METADATA
telewrap-0.2.1.dist-info/WHEEL
telewrap-0.2.1.dist-info/entry_points.txt
telewrap-0.2.1.dist-info/RECORD
