Metadata-Version: 2.1
Name: telewrap
Version: 0.2.1
Summary: Telewrap CLI
Author: Maimonator
Requires-Python: >=3.8
Classifier: Programming Language :: Python :: 3
Classifier: Programming Language :: Python :: 3.8
Classifier: Programming Language :: Python :: 3.9
Classifier: Programming Language :: Python :: 3.10
Classifier: Programming Language :: Python :: 3.11
Requires-Dist: click (>=8.0.0)
Requires-Dist: python-telegram-bot (>=20.1)
